{
  "entries/Adaptive.md": {
    "updated": "",
    "commit": ""
  },
  "entries/Admin.md": {
    "updated": "",
    "commit": ""
  },
  "entries/Alcohol-Induced-Dissociation.md": {
    "updated": "",
    "commit": ""
  },
  "entries/Alexithymia.md": {
    "updated": "",
    "commit": ""
  },
  "entries/Alter.md": {
    "updated": "",
    "commit": ""
  },
  "entries/Alterhuman.md": {
    "updated": "",
    "commit": ""
  },
  "entries/Another-Me-DID-Depictions.md": {
    "updated": "",
    "commit": ""
  },
  "entries/Anxiety.md": {
    "updated": "",
    "commit": ""
  },
  "entries/Apparently-Normal-Part-Emotional-Part-Model.md": {
    "updated": "",
    "commit": ""
  },
  "entries/Attention-Deficit-Hyperactivity-Disorder-ADHD.md": {
    "updated": "",
    "commit": ""
  },
  "entries/Autism-Spectrum-Disorder.md": {
    "updated": "",
    "commit": ""
  },
  "entries/Autopilot.md": {
    "updated": "",
    "commit": ""
  },
  "entries/Back-Being-Back.md": {
    "updated": "",
    "commit": ""
  },
  "entries/Bias.md": {
    "updated": "",
    "commit": ""
  },
  "entries/Bipolar-Disorders.md": {
    "updated": "",
    "commit": ""
  },
  "entries/Blending.md": {
    "updated": "",
    "commit": ""
  },
  "entries/Body-Ownership.md": {
    "updated": "",
    "commit": ""
  },
  "entries/Borderline-Personality-Disorder-BPD.md": {
    "updated": "",
    "commit": ""
  },
  "entries/Bu-Ke-Raoshu-De-Ta-Multiplicity-Narrative.md": {
    "updated": "",
    "commit": ""
  },
  "entries/CPTSD.md": {
    "updated": "",
    "commit": ""
  },
  "entries/Caregiver.md": {
    "updated": "",
    "commit": ""
  },
  "entries/Co-Consciousness.md": {
    "updated": "",
    "commit": ""
  },
  "entries/Co-Fronting.md": {
    "updated": "",
    "commit": ""
  },
  "entries/Consciousness-Modification.md": {
    "updated": "",
    "commit": ""
  },
  "entries/Core.md": {
    "updated": "",
    "commit": ""
  },
  "entries/DID.md": {
    "updated": "",
    "commit": ""
  },
  "entries/Delirium.md": {
    "updated": "",
    "commit": ""
  },
  "entries/Depersonalization-Derealization-Disorder-DPDR.md": {
    "updated": "",
    "commit": ""
  },
  "entries/Depersonalization.md": {
    "updated": "",
    "commit": ""
  },
  "entries/Depressive-Disorders.md": {
    "updated": "",
    "commit": ""
  },
  "entries/Disorientation.md": {
    "updated": "",
    "commit": ""
  },
  "entries/Dissociation.md": {
    "updated": "",
    "commit": ""
  },
  "entries/Dissociative-Amnesia-DA.md": {
    "updated": "",
    "commit": ""
  },
  "entries/Dostoevsky-The-Double-Self-Division.md": {
    "updated": "",
    "commit": ""
  },
  "entries/Emmengard-Classification.md": {
    "updated": "",
    "commit": ""
  },
  "entries/Exomemory.md": {
    "updated": "",
    "commit": ""
  },
  "entries/External-Projection.md": {
    "updated": "",
    "commit": ""
  },
  "entries/Family-Systems-Xianyu.md": {
    "updated": "",
    "commit": ""
  },
  "entries/Fauxmain.md": {
    "updated": "",
    "commit": ""
  },
  "entries/Fight-Club-1999-Identity-Metaphor.md": {
    "updated": "",
    "commit": ""
  },
  "entries/Flashback.md": {
    "updated": "",
    "commit": ""
  },
  "entries/Fragment.md": {
    "updated": "",
    "commit": ""
  },
  "entries/Front-Fronting.md": {
    "updated": "",
    "commit": ""
  },
  "entries/Functional-Dissociation.md": {
    "updated": "",
    "commit": ""
  },
  "entries/Fusion.md": {
    "updated": "",
    "commit": ""
  },
  "entries/Gatekeeper.md": {
    "updated": "",
    "commit": ""
  },
  "entries/Grounding.md": {
    "updated": "",
    "commit": ""
  },
  "entries/Hatsune-Miku-Virtual-Idol-Tulpa-Boundary.md": {
    "updated": "",
    "commit": ""
  },
  "entries/Head-Pressure.md": {
    "updated": "",
    "commit": ""
  },
  "entries/Headspace-Inner-World.md": {
    "updated": "",
    "commit": ""
  },
  "entries/Host.md": {
    "updated": "",
    "commit": ""
  },
  "entries/Iatrogenic-System.md": {
    "updated": "",
    "commit": ""
  },
  "entries/Imaginary-Companion.md": {
    "updated": "",
    "commit": ""
  },
  "entries/Independence.md": {
    "updated": "",
    "commit": ""
  },
  "entries/Integration.md": {
    "updated": "",
    "commit": ""
  },
  "entries/Internal-Self-Helper-ISH.md": {
    "updated": "",
    "commit": ""
  },
  "entries/Intrusive-Thoughts.md": {
    "updated": "",
    "commit": ""
  },
  "entries/Iteration.md": {
    "updated": "",
    "commit": ""
  },
  "entries/Kafka-Metamorphosis-Identity-Dissolution.md": {
    "updated": "",
    "commit": ""
  },
  "entries/Little.md": {
    "updated": "",
    "commit": ""
  },
  "entries/Lovecraft-Tulpa-Motifs.md": {
    "updated": "",
    "commit": ""
  },
  "entries/Madoka-Magica-Kyubey-Otherness.md": {
    "updated": "",
    "commit": ""
  },
  "entries/Main.md": {
    "updated": "",
    "commit": ""
  },
  "entries/Mania.md": {
    "updated": "",
    "commit": ""
  },
  "entries/Meditation.md": {
    "updated": "",
    "commit": ""
  },
  "entries/Memory-Holder.md": {
    "updated": "",
    "commit": ""
  },
  "entries/Memory-Shielding.md": {
    "updated": "",
    "commit": ""
  },
  "entries/Mixed-Systems-Xianyu.md": {
    "updated": "",
    "commit": ""
  },
  "entries/Mr-Robot-DID-Narrative.md": {
    "updated": "",
    "commit": ""
  },
  "entries/Narcissistic-Personality-Disorder-NPD.md": {
    "updated": "",
    "commit": ""
  },
  "entries/Nonexistent-You-And-Me-Tulpa-Lilith.md": {
    "updated": "",
    "commit": ""
  },
  "entries/OCD.md": {
    "updated": "",
    "commit": ""
  },
  "entries/OSDD.md": {
    "updated": "",
    "commit": ""
  },
  "entries/Original.md": {
    "updated": "",
    "commit": ""
  },
  "entries/PTSD.md": {
    "updated": "",
    "commit": ""
  },
  "entries/Paranoia-Agent-Collective-Consciousness.md": {
    "updated": "",
    "commit": ""
  },
  "entries/Partial-Dissociative-Identity-Disorder-PDID.md": {
    "updated": "",
    "commit": ""
  },
  "entries/Pathological-Dissociation.md": {
    "updated": "",
    "commit": ""
  },
  "entries/Performer-Executive.md": {
    "updated": "",
    "commit": ""
  },
  "entries/Permissions.md": {
    "updated": "",
    "commit": ""
  },
  "entries/Persecutor.md": {
    "updated": "",
    "commit": ""
  },
  "entries/Persona.md": {
    "updated": "",
    "commit": ""
  },
  "entries/Plurality-Basics.md": {
    "updated": "2025-10-01T21:56:52+08:00",
    "commit": "e488ce9626fe8c3c8d99e8db956cd7f502652537"
  },
  "entries/Plurality.md": {
    "updated": "",
    "commit": ""
  },
  "entries/Polyfragmented.md": {
    "updated": "",
    "commit": ""
  },
  "entries/Projection.md": {
    "updated": "",
    "commit": ""
  },
  "entries/Protector.md": {
    "updated": "",
    "commit": ""
  },
  "entries/Reconstruction.md": {
    "updated": "",
    "commit": ""
  },
  "entries/Regression-In-Psychology.md": {
    "updated": "",
    "commit": ""
  },
  "entries/Schizophrenia-SC.md": {
    "updated": "",
    "commit": ""
  },
  "entries/Sense-Of-Presence.md": {
    "updated": "",
    "commit": ""
  },
  "entries/Sequestration.md": {
    "updated": "",
    "commit": ""
  },
  "entries/Servitor.md": {
    "updated": "",
    "commit": ""
  },
  "entries/Single-Class-Systems-Xianyu.md": {
    "updated": "",
    "commit": ""
  },
  "entries/Somatic-Symptom-Disorder-SSD.md": {
    "updated": "",
    "commit": ""
  },
  "entries/Soul-Linked-Systems-Xianyu.md": {
    "updated": "",
    "commit": ""
  },
  "entries/Soulbond.md": {
    "updated": "",
    "commit": ""
  },
  "entries/Split-2016-DID-Representation.md": {
    "updated": "",
    "commit": ""
  },
  "entries/Spontaneous.md": {
    "updated": "",
    "commit": ""
  },
  "entries/Stress-Response.md": {
    "updated": "",
    "commit": ""
  },
  "entries/Switch.md": {
    "updated": "",
    "commit": ""
  },
  "entries/Sybil-1976-Cultural-Prototype.md": {
    "updated": "",
    "commit": ""
  },
  "entries/System-Roles.md": {
    "updated": "",
    "commit": ""
  },
  "entries/System.md": {
    "updated": "",
    "commit": ""
  },
  "entries/Teen.md": {
    "updated": "",
    "commit": ""
  },
  "entries/Three-Faces-Of-Eve-1957-Dissociation.md": {
    "updated": "",
    "commit": ""
  },
  "entries/Touhou-Tulpa-Fandom.md": {
    "updated": "",
    "commit": ""
  },
  "entries/Trauma.md": {
    "updated": "",
    "commit": ""
  },
  "entries/Trigger.md": {
    "updated": "",
    "commit": ""
  },
  "entries/Tulpa.md": {
    "updated": "",
    "commit": ""
  },
  "entries/Tulpish.md": {
    "updated": "",
    "commit": ""
  },
  "entries/United-States-Of-Tara-System-Daily-Life.md": {
    "updated": "",
    "commit": ""
  },
  "entries/Visualization-Imagination.md": {
    "updated": "",
    "commit": ""
  },
  "entries/Xianyu-Theory-Niche-Classification.md": {
    "updated": "",
    "commit": ""
  }
}